aslabs/dependencies/near/__init__.py
aslabs/dependencies/near/near.py
aslabs_dependencies_near-0.0.6.dist-info/WHEEL
aslabs_dependencies_near-0.0.6.dist-info/METADATA
aslabs_dependencies_near-0.0.6.dist-info/RECORD
